py_lets_be_quickly_rational/__init__.py
py_lets_be_quickly_rational/constants.py
py_lets_be_quickly_rational/erf_cody.py
py_lets_be_quickly_rational/exceptions.py
py_lets_be_quickly_rational/lets_be_rational.py
py_lets_be_quickly_rational/normaldistribution.py
py_lets_be_quickly_rational/numba_helper.py
py_lets_be_quickly_rational/rationalcubic.py
py_lets_be_quickly_rational-1.0.1.dist-info/LICENSE
py_lets_be_quickly_rational-1.0.1.dist-info/METADATA
py_lets_be_quickly_rational-1.0.1.dist-info/WHEEL
py_lets_be_quickly_rational-1.0.1.dist-info/top_level.txt
py_lets_be_quickly_rational-1.0.1.dist-info/RECORD
