Metadata-Version: 2.1
Name: py-lets-be-quickly-rational
Version: 1.0.1
Summary: Pure python implementation of Peter Jaeckel's LetsBeRational.
Home-page: https://github.com/tmcnitt/py_lets_be_quickly_rational
Maintainer: Troy McNitt
Maintainer-email: troy.mcnitt@gmail.com
License: MIT
Platform: UNKNOWN
License-File: LICENSE
Requires-Dist: numpy
